README.rst
setup.py
generate_cloud_payments_cryptogram/__init__.py
generate_cloud_payments_cryptogram/core.py
generatecpcryptogram.egg-info/PKG-INFO
generatecpcryptogram.egg-info/SOURCES.txt
generatecpcryptogram.egg-info/dependency_links.txt
generatecpcryptogram.egg-info/requires.txt
generatecpcryptogram.egg-info/top_level.txt