Metadata-Version: 1.0
Name: generatecpcryptogram
Version: 1.1
Summary: UNKNOWN
Home-page: https://github.com/NataliaDeryuzhova/generate_cloud_payments_cryptogram
Author: Natalia Deryuzhova
Author-email: derujovanv1993@gmail.com
License: UNKNOWN
Platform: UNKNOWN
